{
  "indexes": [
    {
      "collectionGroup": "readings",
      "queryScope": "COLLECTION",
      "fields": [
        { "fieldPath": "createdAt", "order": "DESCENDING" },
        { "fieldPath": "status", "order": "ASCENDING" }
      ]
    }
  ],
  "fieldOverrides": [
    {
      "collectionGroup": "coffee_reservations",
      "fieldPath": "expiresAtMs",
      "indexes": [
        { "order": "ASCENDING", "queryScope": "COLLECTION" },
        { "order": "DESCENDING", "queryScope": "COLLECTION" },
        { "order": "ASCENDING", "queryScope": "COLLECTION_GROUP" },
        { "order": "DESCENDING", "queryScope": "COLLECTION_GROUP" }
      ]
    },
    {
      "collectionGroup": "coffee_readings",
      "fieldPath": "retentionExpiresAtMs",
      "indexes": [
        { "order": "ASCENDING", "queryScope": "COLLECTION" },
        { "order": "DESCENDING", "queryScope": "COLLECTION" },
        { "order": "ASCENDING", "queryScope": "COLLECTION_GROUP" },
        { "order": "DESCENDING", "queryScope": "COLLECTION_GROUP" }
      ]
    },
    {
      "collectionGroup": "users",
      "fieldPath": "nextDailyCardAt",
      "indexes": [
        { "order": "ASCENDING", "queryScope": "COLLECTION" },
        { "order": "DESCENDING", "queryScope": "COLLECTION" }
      ]
    },
    {
      "collectionGroup": "users",
      "fieldPath": "coffeeFollowupAt",
      "indexes": [
        { "order": "ASCENDING", "queryScope": "COLLECTION" },
        { "order": "DESCENDING", "queryScope": "COLLECTION" }
      ]
    },
    {
      "collectionGroup": "users",
      "fieldPath": "palmFollowupAt",
      "indexes": [
        { "order": "ASCENDING", "queryScope": "COLLECTION" },
        { "order": "DESCENDING", "queryScope": "COLLECTION" }
      ]
    }
  ]
}
